zhtools/__init__.py
zhtools/api_service.py
zhtools/async_tools.py
zhtools/calculation.py
zhtools/cli.py
zhtools/concurrents.py
zhtools/config.py
zhtools/context_manager.py
zhtools/decorators.py
zhtools/exceptions.py
zhtools/random.py
zhtools/signals.py
zhtools/timetools.py
zhtools/typed.py
zhtools/cache/__init__.py
zhtools/cache/decorators.py
zhtools/cache/storages.py
zhtools/commands/__init__.py
zhtools/commands/version.py
zhtools/data_structs/__init__.py
zhtools/data_structs/convertors.py
zhtools/data_structs/dataclass.py
zhtools/data_structs/enum.py
zhtools/security/__init__.py
zhtools/security/aes.py
zhtools-1.2.3.dist-info/LICENSE
zhtools-1.2.3.dist-info/METADATA
zhtools-1.2.3.dist-info/WHEEL
zhtools-1.2.3.dist-info/entry_points.txt
zhtools-1.2.3.dist-info/top_level.txt
zhtools-1.2.3.dist-info/RECORD
