Metadata-Version: 2.1
Name: zhtools
Version: 1.2.3
Summary: Some simple tool methods like cache, timetools and so on.
Author-email: zhyipeng <zhyipeng@outlook.com>
Classifier: Programming Language :: Python :: 3
Classifier: Operating System :: OS Independent
Requires-Python: >=3.12
License-File: LICENSE
Requires-Dist: wrapt >=1.15.0
Requires-Dist: typer
Requires-Dist: toml
Provides-Extra: httpx
Requires-Dist: httpx ; extra == 'httpx'
Provides-Extra: pycryptodome
Requires-Dist: pycryptodome ; extra == 'pycryptodome'
Provides-Extra: pydantic
Requires-Dist: pydantic ; extra == 'pydantic'
Provides-Extra: redis
Requires-Dist: redis ; extra == 'redis'
